zendesk_sdk/__init__.py
zendesk_sdk/client.py
zendesk_sdk/exceptions.py
zendesk_sdk/models.py
zendesk_sdk/py.typed
idi_zendesk_sdk-0.1.0.dist-info/METADATA
idi_zendesk_sdk-0.1.0.dist-info/WHEEL
idi_zendesk_sdk-0.1.0.dist-info/licenses/LICENSE
idi_zendesk_sdk-0.1.0.dist-info/RECORD
