Metadata-Version: 2.4
Name: idi-zendesk-sdk
Version: 0.1.0
Summary: Zendesk SDK
Project-URL: repository, https://github.com/impressdesigns/zendesk-sdk/
Project-URL: documentation, https://impressdesigns.dev/zendesk-sdk/
Author-email: Bradley Reynolds <bradley.reynolds@impressdesigns.com>
License: MIT
License-File: LICENSE
Requires-Python: >=3.13
Requires-Dist: httpx>=0.27.2
Requires-Dist: pydantic>=2.9.2
Provides-Extra: dev
Requires-Dist: mypy>=1.10.1; extra == 'dev'
Requires-Dist: nox>=2024.4.15; extra == 'dev'
Requires-Dist: pre-commit>=3.7.1; extra == 'dev'
Requires-Dist: ruff>=0.5.2; extra == 'dev'
Provides-Extra: docs
Requires-Dist: furo>=2024.5.6; extra == 'docs'
Requires-Dist: releases>=2.1.1; extra == 'docs'
Requires-Dist: sphinx-autoapi>=3.1.2; extra == 'docs'
Requires-Dist: sphinx>=7.4.4; extra == 'docs'
Provides-Extra: tests
Requires-Dist: coverage>=7.6.1; extra == 'tests'
Requires-Dist: pytest-randomly>=3.15.0; extra == 'tests'
Requires-Dist: pytest>=8.2.2; extra == 'tests'
